PEPPA/LICENSE
PEPPA/PEPPA.py
PEPPA/PEPPA_parser.py
PEPPA/README.md
PEPPA/__init__.py
PEPPA/dependencies/FastTreeMP
PEPPA/dependencies/blastn
PEPPA/dependencies/diamond
PEPPA/dependencies/makeblastdb
PEPPA/dependencies/mmseqs
PEPPA/dependencies/rapidnj
PEPPA/modules/clust.py
PEPPA/modules/configure.py
PEPPA/modules/uberBlast.py
BIO_PEPPA-1.0.dist-info/LICENSE
BIO_PEPPA-1.0.dist-info/METADATA
BIO_PEPPA-1.0.dist-info/WHEEL
BIO_PEPPA-1.0.dist-info/entry_points.txt
BIO_PEPPA-1.0.dist-info/top_level.txt
BIO_PEPPA-1.0.dist-info/RECORD
