Metadata-Version: 2.1
Name: BIO-PEPPA
Version: 1.0
Summary: UNKNOWN
Home-page: https://github.com/zheminzhou/PEPPA
Author: Zhemin Zhou
Author-email: zhemin.zhou@warwick.ac.uk
License: UNKNOWN
Keywords: bioinformatics,microbial,genomics,MLST,pan-genome
Platform: UNKNOWN
Classifier: Development Status :: 5 - Production/Stable
Classifier: Programming Language :: Python :: 3.5
Classifier: Programming Language :: Python :: 3.6
Classifier: Programming Language :: Python :: 3.7
Classifier: Programming Language :: Python :: 3.8
Classifier: License :: OSI Approved :: GNU General Public License v3 (GPLv3)
Classifier: Operating System :: OS Independent
Requires-Dist: ete3 (>=3.1.1)
Requires-Dist: numba (>=0.47.0)
Requires-Dist: numpy (>=1.18.1)
Requires-Dist: pandas (>=1.0.1)
Requires-Dist: scipy (>=1.3.2)
